LICENSE
mkprofile/__init__.py
mkprofile/__main__.py
mkprofile/mobileconfig.py
mkprofile-2.0.0.dist-info/entry_points.txt
mkprofile-2.0.0.dist-info/LICENSE
mkprofile-2.0.0.dist-info/WHEEL
mkprofile-2.0.0.dist-info/METADATA
mkprofile-2.0.0.dist-info/RECORD
